xbox_controller/__init__.py
xbox_controller/cli.py
xbox_controller/controller.py
xbox_controller/utils.py
xbox_controller_py-1.0.0.dist-info/licenses/LICENSE
xbox_controller_py-1.0.0.dist-info/METADATA
xbox_controller_py-1.0.0.dist-info/WHEEL
xbox_controller_py-1.0.0.dist-info/entry_points.txt
xbox_controller_py-1.0.0.dist-info/top_level.txt
xbox_controller_py-1.0.0.dist-info/RECORD
